LICENSE
MANIFEST.in
README.rst
setup.py
django_ma_settings.egg-info/PKG-INFO
django_ma_settings.egg-info/SOURCES.txt
django_ma_settings.egg-info/dependency_links.txt
django_ma_settings.egg-info/top_level.txt
ma_settings/__init__.py
ma_settings/admin.py
ma_settings/master_settings.py
ma_settings/models.py
ma_settings/tests.py
ma_settings/urls.py
ma_settings/views.py
ma_settings/management/__init__.py
ma_settings/management/commands/__init__.py
ma_settings/management/commands/init_settings.py
ma_settings/migrations/0001_initial.py
ma_settings/migrations/__init__.py
ma_settings/templates/ma_settings/base.html
ma_settings/templates/ma_settings/home.html