Metadata-Version: 1.1
Name: django-ma-settings
Version: 1.0.3
Summary: A simple Django app to have simple typed settings.
Home-page: https://github.com/MasterAlish/django-ma-settings
Author: Alisher Alikulov
Author-email: masteraalish@gmail.com
License: BSD License
Keywords: django-settings
Platform: UNKNOWN
Classifier: Environment :: Web Environment
Classifier: Framework :: Django
Classifier: Intended Audience :: Developers
Classifier: License :: OSI Approved :: BSD License
Classifier: Operating System :: OS Independent
Classifier: Programming Language :: Python
Classifier: Programming Language :: Python :: 2.7
Classifier: Programming Language :: Python :: 3
Classifier: Topic :: Internet :: WWW/HTTP
Classifier: Topic :: Internet :: WWW/HTTP :: Dynamic Content
